mdx_spanner/__init__.py
mdx_spanner/mdx_spanner.py
mdx_spanner-0.1.0.dist-info/LICENSE
mdx_spanner-0.1.0.dist-info/METADATA
mdx_spanner-0.1.0.dist-info/WHEEL
mdx_spanner-0.1.0.dist-info/top_level.txt
mdx_spanner-0.1.0.dist-info/RECORD
