Metadata-Version: 2.1
Name: mdx_spanner
Version: 0.1.0
Summary: Span table cols and rows in MkDocs
Home-page: https://gitlab.com/mschleeweiss/mdx_spanner
Author: Marc Schleeweiß
Author-email: mschleeweiss@gmail.com
Project-URL: Bug Tracker, https://gitlab.com/mschleeweiss/mdx_spanner/-/issues
Classifier: Programming Language :: Python :: 3
Classifier: License :: OSI Approved :: MIT License
Classifier: Operating System :: OS Independent
Requires-Python: >=3.6
License-File: LICENSE
Requires-Dist: Markdown>=3.0
